{
    "fullName": {
        "message": "سبونسر بلوك لليوتيوب - تخطي الرعاية الاعلانية",
        "description": "Name of the extension."
    },
    "Description": {
        "message": "تخطي الرعاية الاعلانية ، التسول في الاشتراك والمزيد على مقاطع الفيديو على اليوتيوب. التبليغ عن الرعايه الاعلانيه علي مقاطع الفيديو التي تشاهدها لتوفير وقتك و وقت الآخرين.",
        "description": "Description of the extension."
    },
    "400": {
        "message": "الخادم قال أن هذا الطلب خاطيء"
    },
    "429": {
        "message": "لقد قدمت الكثير من اوقات الرعاية الاعلانية لهذا الفيديو الواحد، هل أنت متأكد من وجود هذا العدد؟"
    },
    "409": {
        "message": "تم تقديم هذا بالفعل من قبل"
    },
    "channelWhitelisted": {
        "message": "القناة في القائمة البيضاء!"
    },
    "Segment": {
        "message": "جزء"
    },
    "Segments": {
        "message": "أجزاء"
    },
    "SegmentsCap": {
        "message": "فقرات"
    },
    "Chapters": {
        "message": "الفصول"
    },
    "renderAsChapters": {
        "message": "عرض الفقرات كفصول",
        "description": "Refers to drawing segments on the YouTube seek bar as split up chapters, similar to the existing chapter system"
    },
    "showSegmentNameInChapterBar": {
        "message": "إظهار الفقرة الحالية الحالية بجانب وقت الفيديو"
    },
    "upvoteButtonInfo": {
        "message": "التصويت على هذا الإرسال"
    },
    "reportButtonTitle": {
        "message": "إبلاغ"
    },
    "reportButtonInfo": {
        "message": "الإبلاغ عن هذا التقديم كغير صحيح."
    },
    "Dismiss": {
        "message": "إلغاء"
    },
    "Loading": {
        "message": "جاري التحميل..."
    },
    "Hide": {
        "message": "لا تظهر أبداً"
    },
    "hitGoBack": {
        "message": "قم الضغط علي تخطي للوصول إلى المكان الذي أتيت منه."
    },
    "unskip": {
        "message": "الرجوع في التخطي"
    },
    "reskip": {
        "message": "اعاده التخطي"
    },
    "unmute": {
        "message": "إلغاء الكتم"
    },
    "paused": {
        "message": "ايقاف مؤقت"
    },
    "manualPaused": {
        "message": "تم إيقاف الموقت"
    },
    "confirmMSG": {
        "message": "لتحرير أو حذف قيّم فردياً، انقر فوق زر المعلومات أو فتح الإضافة عن طريق النقر على أيقونة الإضافة في الزاوية اليمنى العليا."
    },
    "clearThis": {
        "message": "هل أنت متأكد أنك تريد حذف هذا؟\n\n"
    },
    "Unknown": {
        "message": "حدث خطأ في إرسال توقيت الرعاة الخاص بك، الرجاء المحاولة مرة أخرى لاحقاً."
    },
    "sponsorFound": {
        "message": "يحتوي هذا الفيديو على أجزاء في قاعدة البيانات!"
    },
    "sponsor404": {
        "message": "لم يتم العثور على أجزاء"
    },
    "sponsorStart": {
        "message": "يبدأ الجزء الآن"
    },
    "sponsorEnd": {
        "message": "ينتهي الجزء الآن"
    },
    "sponsorCancel": {
        "message": "إلغاء إنشاء جزء"
    },
    "noVideoID": {
        "message": "لم يتم العثور على فيديو يوتيوب.\nإذا كان هذا غير صحيح، قم بتحديث الصفحة."
    },
    "refreshSegments": {
        "message": "تحديث الأجزاء"
    },
    "success": {
        "message": "تم بنجاح!"
    },
    "voted": {
        "message": "تم التصويت!"
    },
    "serverDown": {
        "message": "يبدو أن الخادم معطل. تواصل مع المطوّر على الفور."
    },
    "connectionError": {
        "message": "حدث خطأ في الاتصال. رمز الخطأ: "
    },
    "segmentsStillLoading": {
        "message": "لا تزل الفقرات قيد التحميل..."
    },
    "clearTimes": {
        "message": "مسح الفقرات"
    },
    "openPopup": {
        "message": "فتح نافذة SponsorBlock المنبثقة"
    },
    "closePopup": {
        "message": "إغلاق النافذة المنبثقة"
    },
    "closeIcon": {
        "message": "أيقونة الإغلاق"
    },
    "OpenSubmissionMenu": {
        "message": "قتح قائمة التقديم"
    },
    "sortSegments": {
        "message": "فرز الفقرات"
    },
    "submitCheck": {
        "message": "هل أنت متأكد أنك تريد إرسال هذا؟"
    },
    "whitelistChannel": {
        "message": "إضافة القناة إلى القائمة البيضاء"
    },
    "removeFromWhitelist": {
        "message": "إزالة القناة من القائمة البيضاء"
    },
    "voteOnTime": {
        "message": "صوّت لجزء"
    },
    "Submissions": {
        "message": "المشاركات"
    },
    "savedPeopleFrom": {
        "message": "لقد وفّرت على الناس "
    },
    "viewLeaderboard": {
        "message": "المتصدرين"
    },
    "recordTimesDescription": {
        "message": "تقديم"
    },
    "submissionEditHint": {
        "message": "سيظهر تحرير القسم بعد النقر على تقديم",
        "description": "Appears in the popup to inform them that editing has been moved to the video player."
    },
    "popupHint": {
        "message": "تلميح: يمكنك إعداد اختصارات مفاتيح للتقديم في الخيارات"
    },
    "clearTimesButton": {
        "message": "مسح الأوقات"
    },
    "Username": {
        "message": "اسم المستخدم"
    },
    "setUsername": {
        "message": "تعيين اسم مستخدم"
    },
    "copyPublicID": {
        "message": "نسخ معرف المستخدم العام"
    },
    "copySegmentID": {
        "message": "نسخ معرف الفقرة"
    },
    "hideThis": {
        "message": "إخفاء هذا"
    },
    "Options": {
        "message": "خيارات"
    },
    "showButtons": {
        "message": "إظهار الأزرار على مشغل اليوتيوب"
    },
    "hideButtons": {
        "message": "إخفاء الأزرار على مشغل اليوتيوب"
    },
    "hideButtonsDescription": {
        "message": "يخفي الأزرار التي تظهر على مشغل اليوتيوب لإرسال فقرات للتخطي."
    },
    "showSkipButton": {
        "message": "إبقاء زر \"تخطي للابراز\" على المشغّل"
    },
    "showInfoButton": {
        "message": "إظهار زر \"معلومات\" على مشغّل اليوتيوب"
    },
    "hideInfoButton": {
        "message": "إخفاء زر \"معلومات\" على مشغّل اليوتيوب"
    },
    "autoHideInfoButton": {
        "message": "إخفاء تلقائي لزر \"معلومات\""
    },
    "hideDeleteButton": {
        "message": "إخفاء زر \"حذف\" على مشغّل اليوتيوب"
    },
    "showDeleteButton": {
        "message": "إظهار زر \"حذف\" على مشغّل اليوتيوب"
    },
    "enableViewTracking": {
        "message": "تفعيل تتبع مرات التخطي"
    },
    "whatViewTracking": {
        "message": "تتعقب هذه المِيزة الفقرات التي تخطيتها للسماح للمستخدمين بمعرفة مقدار مساعدة تقديماتهم للآخرين و تستخدم كمقياس جنبًا إلى جنب مع الأصوات الايجابية لضمان عدم وصول التقديمات الخاطئة إلى قاعدة البيانات. ترسل الإضافة رسالة للخادم كل مرة تتخطى فيها فقرة. نأمل ألا يغير معظم الناس هذا الاعداد بحيث تكون ارقام مرات العرض دقيقة. :)"
    },
    "enableViewTrackingInPrivate": {
        "message": "تفعيل تتبع مرات التخطي في علامات التبويب الخاصة / التصفح المتخفي"
    },
    "enableTrackDownvotes": {
        "message": "حفظ الأصوات السلبية للفقرات"
    },
    "whatTrackDownvotes": {
        "message": "أي فقرات قمت بالتصويت السلبي لها ستبقى مخفية حتى بعد تحديث الصفحة"
    },
    "trackDownvotesWarning": {
        "message": "تحذير: سيؤدي تعطيل هذا إلى حذف جميع الأصوات السلبية التي تم تخزينها مسبقًا"
    },
    "enableQueryByHashPrefix": {
        "message": "الاستعلام عن طريق بادئة التجزئة"
    },
    "whatQueryByHashPrefix": {
        "message": "بدلاً من طلب الفقرات من الخادم باستخدام معرف الفيديو ، يتم إرسال الأحرف الأربعة الأولى من تجزئة معرف الفيديو. سيرسل هذا الخادم بالمقابل بينات كل الفيديوهات بتجزئات مشابهة."
    },
    "enableRefetchWhenNotFound": {
        "message": "إعادة جلب الفقرات في الفيديوهات الجديدة"
    },
    "whatRefetchWhenNotFound": {
        "message": "إذ كان الفيديو جديد، ولم يتم العثور على أي فقرات، سيتم أستمرار البحث عن فقرات كل بضع دقائق بينما تشاهد."
    },
    "enableShowCategoryWithoutPermission": {
        "message": "إظهار الفئات في قائمة التقديم حتى دون إذن التقديم"
    },
    "whatShowCategoryWithoutPermission": {
        "message": "تحتاج بعض الفئات إلى إذن لتقديمها بسبب الحد الأدنى من متطلبات السمعة"
    },
    "showNotice": {
        "message": "إظهار الإشعار مرة أخرى"
    },
    "showSkipNotice": {
        "message": "إظهار إشعار بعد تخطي فقرة ما"
    },
    "showCategoryGuidelines": {
        "message": "إظهار مساعدة الفئة"
    },
    "noticeVisibilityMode0": {
        "message": "الحجم الكامل لإشعارات التخطي"
    },
    "noticeVisibilityMode1": {
        "message": "إشعارات تخطي صغيرة للتخطي التلقائي"
    },
    "noticeVisibilityMode2": {
        "message": "حجم صغير لإشعارات التخطي"
    },
    "noticeVisibilityMode3": {
        "message": "إشعارات تخطي متلاشية للتخطي التلقائي"
    },
    "noticeVisibilityMode4": {
        "message": "إشعارات تخطي متلاشية"
    },
    "longDescription": {
        "message": "يتيح لك SponsorBlock تخطي الرعايات و المقدمات و المؤخرات و التذكيرات بالاشتراك و اجزاء أخرى مزعجة من فيديوهات اليوتيوب. SponsorBlock إضافة متصفح مصدّرة جماعيا يتيح لأي احد بتقديم أوقات البدء و الانتهاء للفقرات المرعية و فقرات اخرى من فيديوهات اليوتيوب. و بمجرد أن يقدم شخص واحد هذه المعلونات سيتخطى كل شخص آخر مع هذه الإضافة الفقرة المرعية. بالامكان أيضا تخطي الأجزاء الغير موسيقية من فيديوات الموسيقى.",
        "description": "Full description of the extension on the store pages."
    },
    "website": {
        "message": "موقع الويب",
        "description": "Used on Firefox Store Page"
    },
    "sourceCode": {
        "message": "الشفرة المصدرية",
        "description": "Used on Firefox Store Page"
    },
    "noticeUpdate": {
        "message": "تم تحديث الإشعار!",
        "description": "The first line of the message displayed after the notice was upgraded."
    },
    "noticeUpdate2": {
        "message": "اذا كانت لا تزال تزعجك، اضغط على زر لا تظهر أبداً.",
        "description": "The second line of the message displayed after the notice was upgraded."
    },
    "setSkipShortcut": {
        "message": "تخطي الفقرة",
        "description": "Keybind label"
    },
    "setStartSponsorShortcut": {
        "message": "بدء/إيقاف الفقرة",
        "description": "Keybind label"
    },
    "setSubmitKeybind": {
        "message": "تقديم الفقرات",
        "description": "Keybind label"
    },
    "nextChapterKeybind": {
        "message": "الفصل التالي",
        "description": "Keybind label"
    },
    "previousChapterKeybind": {
        "message": "الفصل السابق",
        "description": "Keybind label"
    },
    "keybindDescription": {
        "message": "حدد مفتاح عن طريق كتابته واختار أي \"مفاتيح تعديل\" ترغب في استخدامها."
    },
    "0": {
        "message": "انتهت مهلة الاتصال. تحقق من اتصالك بالإنترنت. إذا كان إتصالك بالإنترنت يعمل، قد يكون الخادم محمل أكثر من اللازم أو معطل حاليا."
    },
    "disableSkipping": {
        "message": "التخطي مفعل"
    },
    "enableSkipping": {
        "message": "التخطي معطل"
    },
    "yourWork": {
        "message": "عملك",
        "description": "Used to describe the section that will show you the statistics from your submissions."
    },
    "502": {
        "message": "يبدو أن الخادم محمَّل أكثر من اللازم. حاول مرة أخرى في بضع ثوان."
    },
    "errorCode": {
        "message": "رمز الخطأ: "
    },
    "skip": {
        "message": "تخطي"
    },
    "mute": {
        "message": "كتم"
    },
    "full": {
        "message": "الفيديو كامل",
        "description": "Used for the name of the option to label an entire video as sponsor or self promotion."
    },
    "skip_category": {
        "message": "تخطي {0}؟"
    },
    "mute_category": {
        "message": "كتم {0}؟"
    },
    "skip_to_category": {
        "message": "تخطي إلى {0}؟",
        "description": "Used for skipping to things (Skip to Highlight)"
    },
    "skipped": {
        "message": "تم تخطي {0}",
        "description": "Example: Sponsor Skipped"
    },
    "muted": {
        "message": "تم كتم {0}",
        "description": "Example: Sponsor Muted"
    },
    "skipped_to_category": {
        "message": "تم التخطي إلى {0}",
        "description": "Used for skipping to things (Skipped to Highlight)"
    },
    "disableAutoSkip": {
        "message": "تعطيل التخطي التلقائي"
    },
    "enableAutoSkip": {
        "message": "تفعيل التخطي التلقائي"
    },
    "audioNotification": {
        "message": "إشعار صوتي عند التخطي"
    },
    "audioNotificationDescription": {
        "message": "إشعار صوتي عند التخطي سيشغّل صوت كلما يتم تخطي فقرة ما. إن كان معطل (أو التخطي التلقائي معطل) لن يتم تشغيل صوت."
    },
    "showTimeWithSkips": {
        "message": "أظهر مدة الفيديو من دون الفقرات المتخطية"
    },
    "showTimeWithSkipsDescription": {
        "message": "هذه المدة ستظهر بين قوسين بجانب الوقت الحالي أسفل شريط التمرير. يظهر مجموع مدة الفيديو مطروح من أي فقرات. يشمل الفقرات المحددة فقط على أنها \"إظهار في شريط التمرير\"."
    },
    "youHaveSkipped": {
        "message": "قمت بتخطي "
    },
    "minLower": {
        "message": "دقيقة"
    },
    "minsLower": {
        "message": "دقيقة"
    },
    "hourLower": {
        "message": "ساعة"
    },
    "hoursLower": {
        "message": "ساعة"
    },
    "youHaveSavedTime": {
        "message": "لقد وفّرت على الناس",
        "description": "You've saved people from 887,362 segments (236d 15h 5.3 minutes of their lives)."
    },
    "youHaveSavedTimeEnd": {
        "message": " من حياتهم",
        "description": "You've saved people from 887,362 segments (236d 15h 5.3 minutes of their lives)."
    },
    "statusReminder": {
        "message": "تحقق من status.sponsor.ajay.app لمعرفة حالة الخادم."
    },
    "changeUserID": {
        "message": "استيراد/تصدير معرف المستخدم السري الخاص بك"
    },
    "whatChangeUserID": {
        "message": "يجب أن يبقى هذا سريًا. هذا مثل كلمة المرور ولا ينبغي مشاركته مع أي شخص. إذا كان شخص ما يملك هذا، فيمكنه انتحال شخصيتك. إذا كنت تبحث عن معرف المستخدم العام الخاص بك، انقر فوق أيقونة الحافظة في المنبثق."
    },
    "setUserID": {
        "message": "تعيين معرف المستخدم السري"
    },
    "userIDChangeWarning": {
        "message": "تحذير: تغيير معرف المستخدم السري دائم. هل أنت متأكد من رغبتك في القيام بهذا؟ تأكد من النسخ الاحتياطي للمعرف القديم تحسبا."
    },
    "createdBy": {
        "message": "أنشئت من قِبل"
    },
    "supportOtherSites": {
        "message": "دعم مواقع يوتيوب الطرف الثالث"
    },
    "supportOtherSitesDescription": {
        "message": "دعم منصات يوتيوب الطرف ثالث. لتمكين الدعم، يجب عليك قبول التصاريح الإضافية.",
        "description": "This replaces the 'supports Invidious' option because it now works on other YouTube sites such as Cloudtube"
    },
    "supportedSites": {
        "message": "المواقع المدعومة: "
    },
    "optionsInfo": {
        "message": "تفعيل دعم Invidious، تعطيل التخطي التلقائي، إخفاء الأزرار و المزيد."
    },
    "addInvidiousInstance": {
        "message": "إضافة حالة لمنصة يوتيوب طرف ثالث"
    },
    "addInvidiousInstanceDescription": {
        "message": "اضافة حالة خاصة. يجب ان يحتوي على المجال فقط. مثال: invidious.ajay.app"
    },
    "add": {
        "message": "أضِف"
    },
    "addInvidiousInstanceError": {
        "message": "هذا مجال غير صالح. يجب ان يحتوي على جزء المجال فقط. مثال: invidious.ajay.app"
    },
    "resetInvidiousInstance": {
        "message": "إعادة تعيين قائمة حالات Invidious"
    },
    "resetInvidiousInstanceAlert": {
        "message": "أنت على وشك إعادة تعيين قائمة حالات Invidious"
    },
    "currentInstances": {
        "message": "الحالات الحالية:"
    },
    "minDuration": {
        "message": "المدة الدنيا (ثوان):"
    },
    "minDurationDescription": {
        "message": "الاقسام الاصغر من القيمة المحددة لن يتم تخطيها ولا عرضها في المشغل."
    },
    "enableManualSkipOnFullVideo": {
        "message": "استخدام التخطي اليدوي عند وجود لصيقة للفيديو باكمله"
    },
    "whatManualSkipOnFullVideo": {
        "message": "للاشخاص الراغبين بمشاهدة الفيديو دون انقطاع اذا كان مُرعى بالكامل أو دعاية شخصية."
    },
    "skipNoticeDuration": {
        "message": "مدة اشعار التخطي (ثوان):"
    },
    "skipNoticeDurationDescription": {
        "message": "سيبقى اشعار التخطي على الشاشة للمدة المحددة على الأقل. للتخطي اليدوي، قد يكون مرئيًا لفترة أطول."
    },
    "shortCheck": {
        "message": "التقديم التالي أقصر من مدة التقديم الأدنى المحددة. قد يعني هذا أن التقديم قد يكون موجود بالفعل ولكن يتم تجاهله بسبب هذا الخيار. هل أنت متأكد من رغبتك في التقديم؟"
    },
    "liveOrPremiere": {
        "message": "لا يسمح بالتقديم على بث مباشر أو بث العرض الأولي للفيديو. الرجاء الانتظار حتى ينتهي، ثم قم بتحديث الصفحة و تحقق أن الفقرات لا تزال صالحة."
    },
    "showUploadButton": {
        "message": "إظهار زر الرفع"
    },
    "customServerAddress": {
        "message": "عنوان خادم SponsorBlock"
    },
    "customServerAddressDescription": {
        "message": "العنوان الذي يستعمله SponsorBlock لاجراء اتصالات للخادم.\nإلا إذا كان لديك حالة خادم خاصة بك، لا ينبغي تغيير هذا."
    },
    "dataFetchingServerAddress": {
        "message": "عنوان خادم جلب البينات"
    },
    "dataFetchingServerAddressDescription": {
        "message": "العنوان المستخدم لاجراء اتصالات لخادم جلب البينات.\nإلا إذا كان لديك حالة خادم خاصة بك، لا ينبغي تغيير هذا."
    },
    "thumbnailCacheServerAddress": {
        "message": "عنوان خادم تخزين الصور المصغرة"
    },
    "save": {
        "message": "حفظ"
    },
    "reset": {
        "message": "إعادة تعيين"
    },
    "customAddressError": {
        "message": "هذا العنوان ليس في الشكل الصحيح. تأكد من أن لديك http:// أو https:// في البداية و عدم تواجد شريط مائل في النهاية."
    },
    "areYouSureReset": {
        "message": "هل أنت متيقِّن من رغبتك في إعادة تعيين هذا؟"
    },
    "mobileUpdateInfo": {
        "message": "m.youtube.com مدعوم الآن"
    },
    "exportOptions": {
        "message": "إستيراد/تصدير جميع الإعدادات"
    },
    "exportOptionsCopy": {
        "message": "تعديل/نسخ"
    },
    "exportOptionsDownload": {
        "message": "حفظ إلى ملف"
    },
    "exportOptionsUpload": {
        "message": "تحميل من ملف"
    },
    "setOptions": {
        "message": "تعيين الخيارات"
    },
    "exportOptionsWarning": {
        "message": "تحذير: تغيير الخيارات دائم و قد يخرب تثبيتك. هل أنت متأكد من رغبتك في القيام بهذا؟ تأكد من النسخ الاحتياطي للتثبيت القديم تحسبا."
    },
    "confirmNoticeTitle": {
        "message": "إرسال المقطع"
    },
    "submit": {
        "message": "إرسال"
    },
    "cancel": {
        "message": "إلغاء"
    },
    "delete": {
        "message": "حذف"
    },
    "preview": {
        "message": "معاينة"
    },
    "unsubmitted": {
        "message": "غير مرسلة"
    },
    "inspect": {
        "message": "فحص"
    },
    "edit": {
        "message": "تعديل"
    },
    "copyDebugInformation": {
        "message": "نسخ معلومات التشخيص إلى الحافظة"
    },
    "copyDebugInformationFailed": {
        "message": "فشل في الكتابة إلى الحافظة"
    },
    "copyDebugInformationOptions": {
        "message": "ينسخ المعلومات إلى الحافظة لتقديمها إلى المطور عند تبليغ خلل / عندما يطلب المطور ذلك. تم إزالة معلومات حساسة مثل معرف مستخدمك السري و قنوات القائمة البيضاء وعنوان الخادم المخصص. غير أنه يحتوي على معلومات مثل المستخدم الخاص بك، المتصفح، نظام التشغيل، رقم اصدار الإضافة. "
    },
    "to": {
        "message": "إلى",
        "description": "Used between segments. Example: 1:20 to 1:30"
    },
    "CopiedExclamation": {
        "message": "تم النسخ!",
        "description": "Used after something has been copied to the clipboard. Example: 'Copied!'"
    },
    "generic_guideline1": {
        "message": "يتضمن الانتقالات"
    },
    "generic_guideline2": {
        "message": "يجب أن يستمر الفيديو كأنما لم يتم تخطي شيئا"
    },
    "category_sponsor": {
        "message": "رعاية"
    },
    "category_sponsor_description": {
        "message": "الدعايات المدفوعة و التوصيات المدفوعة و الإعلانات المباشرة. ليس للدعاية الذاتية أو اعلانات مجانية لأسباب انسانية/مبدعين/مواقع/منتجات يحبونها."
    },
    "category_sponsor_guideline1": {
        "message": "دعايات مدفوعة"
    },
    "category_sponsor_guideline2": {
        "message": "ليس للتبرعات أو منتجات صانع المحتوى"
    },
    "category_selfpromo": {
        "message": "دعاية غير مدفوعة/ذاتية"
    },
    "category_selfpromo_description": {
        "message": "شبيه بـ \"رعاية\" ولكن غير ممولة أو أن تكون دعاية ذاتية. يشمل هذا منتجات صانع المحتوى أو تبرعات او معلومات حول من تعاونوا معهم."
    },
    "category_selfpromo_guideline1": {
        "message": "التبرعات و العضوية و منتجات صانع المحتوى"
    },
    "category_selfpromo_guideline2": {
        "message": "تصريحات شكر مجانية التي لا تضيف إلى الفيديو"
    },
    "category_selfpromo_guideline3": {
        "message": "ليس للمنتجات المصممة من شركات"
    },
    "category_exclusive_access": {
        "message": "وصول حصري"
    },
    "category_exclusive_access_description": {
        "message": "فقط لتوسيم مقاطع فيديو بِرُمَّتها. تستخدم عند عرض الفيديو منتج أو خدمة أو موقع حصلوا عليه مجانا أو بثمن مخفف."
    },
    "category_exclusive_access_pill": {
        "message": "هذا الفيديو يعرض منتج أو خدمة أو موقع حصل صانع المحتوى عليه مجانا أو بثمن مخفف",
        "description": "Short description for this category"
    },
    "category_exclusive_access_guideline1": {
        "message": "الفيديو برمّته يعرض شيء حصل صانع المحتوى عليه مجانا أو بثمن مخفف"
    },
    "category_interaction": {
        "message": "التذكير بالتفاعل (الاشتراك)"
    },
    "category_interaction_description": {
        "message": "عند وجود تذكار قصير للاشتراك أو المتابعة في منتصف محتوى. إذا كان طويل أو حول شيء محدد، يجب أن يكون تحت الترويج الذاتي."
    },
    "category_interaction_guideline1": {
        "message": "تذكيرات قصيرة بالإعجاب أو الاشتراك أو المتابعة"
    },
    "category_interaction_guideline2": {
        "message": "يتضمن تذكيرات غير مباشرة للتعليق"
    },
    "category_interaction_guideline3": {
        "message": "ليس للترويج بشكل عام و انما فقط نداءات لفعل"
    },
    "category_interaction_short": {
        "message": "التذكير بالتفاعل"
    },
    "category_intro": {
        "message": "انترو"
    },
    "category_intro_description": {
        "message": "فاصل زمني بدون محتوى فعلي. يمكن أن يكون توقفًا مؤقتًا أو إطارًا ثابتًا أو تكرار الرسوم المتحركة. لا يتضمن انتقالات تحتوي على معلومات."
    },
    "category_intro_short": {
        "message": "استراحة"
    },
    "category_intro_guideline1": {
        "message": "فاصل بدون محتوى فعلي"
    },
    "category_outro": {
        "message": "الخاتمة/تترات النهاية"
    },
    "category_outro_description": {
        "message": "لائحة المساهمون في العمل أو عند ظهور شاشات النهاية. ليس للاستنتاجات مع معلومات."
    },
    "category_preview": {
        "message": "معاينة/خلاصة"
    },
    "category_preview_description": {
        "message": "مجموعة من اللقطات تُظهر ما هو قادم في هذا الفيديو او في فيديوهات اخرى في سلسلة حيث كل المعلومة مكررة لاحقا في الفيديو."
    },
    "category_preview_guideline2": {
        "message": "موجز الفيديو السابق"
    },
    "category_filler": {
        "message": "حشو خارج عن الموضوع/نكات"
    },
    "category_filler_description": {
        "message": "مشاهد أُضيفت فقط للحشو أو الدعابة و هي غير ضرورية لفهم المحتوي الرئيسي للفيديو. لا ينبغي أن يضم الأجزاء المبينة للسياق أو تفاصيل اضافية. هذه فئة شرسة تنبغي لحين لا تكون في المزاج للـ\"متعة\"."
    },
    "category_filler_short": {
        "message": "حشو"
    },
    "category_filler_guideline1": {
        "message": "مشاهد أُضيفت فقط للحشو أو الدعابة"
    },
    "category_filler_guideline2": {
        "message": "تلهيات، مشاهد خلف الكواليس، إعادة عرض مشاهد سابقة"
    },
    "category_filler_guideline3": {
        "message": "ليس للمشاهد الضرورية لفهم الموضوع"
    },
    "category_music_offtopic": {
        "message": "الموسيقى: مقطع غير موسيقي"
    },
    "category_music_offtopic_description": {
        "message": "فقط للاستخدام في الفيديوات الموسيقية. يجب استعماله فقط لأجزاء من الفيديو الموسيقي التي ليست مغطات بفئة اخرى."
    },
    "category_music_offtopic_short": {
        "message": "غير موسيقي"
    },
    "category_poi_highlight": {
        "message": "ابراز"
    },
    "category_poi_highlight_description": {
        "message": "الجزء من الفيديو الذي يبحث عنه معظم الناس. على غرار تعليقات \"الفيديو يبدأ عند x\"."
    },
    "category_poi_highlight_guideline3": {
        "message": "يمكن التخطي إلى عنوان المقطع أو الصورة المصغرة"
    },
    "category_chapter": {
        "message": "فصل"
    },
    "category_chapter_description": {
        "message": "فصول بأسماء مخصصة تصف اجزاء كبرى من فيديو."
    },
    "category_chapter_guideline1": {
        "message": "لا تذكر أسماء العلامة التجارية الراعية"
    },
    "category_livestream_messages_short": {
        "message": "قراءة الرسالة"
    },
    "autoSkip": {
        "message": "تخطي تلقائي"
    },
    "manualSkip": {
        "message": "تخطي يدوي"
    },
    "showOverlay": {
        "message": "إظهار في شريط التمرير"
    },
    "disable": {
        "message": "تعطيل"
    },
    "autoSkip_POI": {
        "message": "تخطي تلقائي حتى البدء"
    },
    "manualSkip_POI": {
        "message": "اسأل عند تحميل الفيديو"
    },
    "showOverlay_POI": {
        "message": "إظهار في شريط التمرير"
    },
    "showOverlay_full": {
        "message": "إظهار التسمية"
    },
    "showOverlay_chapter": {
        "message": "عرض الفصول"
    },
    "autoSkipOnMusicVideos": {
        "message": "تخطي جميع الاقسام تلقائياً عندما يكون هناك قسم غير موسيقي"
    },
    "muteSegments": {
        "message": "السماح بالاقسام التي تكتم الصوت بدلاً التخطي"
    },
    "fullVideoSegments": {
        "message": "إظهار أيقونة عندما يكون الفيديو بالكامل اعلان",
        "description": "Referring to the category pill that is now shown on videos that are entirely sponsor or entirely selfpromo"
    },
    "previewColor": {
        "message": "لون غير المرسل",
        "description": "Referring to submissions that have not been sent to the server yet."
    },
    "seekBarColor": {
        "message": "لون شريط التمرير"
    },
    "category": {
        "message": "الفئة"
    },
    "skipOption": {
        "message": "خيار التخطي",
        "description": "Used on the options page to describe the ways to skip the segment (auto skip, manual, etc.)"
    },
    "enableTestingServer": {
        "message": "تمكين الخادم التجريبي"
    },
    "bracketNow": {
        "message": "(الآن)"
    },
    "moreCategories": {
        "message": "المزيد من الفئات"
    },
    "chooseACategory": {
        "message": "اختر فئة"
    },
    "enableThisCategoryFirst": {
        "message": "لتقديم فقرات مع الفئة \"{0}\"، يوجب تفعيلها في الخيارات. سيتم تحويلك الى الخيارات فورا.",
        "description": "Used when submitting segments to only let them select a certain category if they have it enabled in the options."
    },
    "youMustSelectACategory": {
        "message": "يوجب تحديد فئة لكل الفقرات المنبغي تقديمها!"
    },
    "bracketStart": {
        "message": "(البداية)"
    },
    "bracketEnd": {
        "message": "(النهاية)"
    },
    "End": {
        "message": "النهاية",
        "description": "Button that skips to the end of a segment"
    },
    "hiddenDueToDownvote": {
        "message": "مخفي: تصويت سلبي"
    },
    "hiddenDueToDuration": {
        "message": "مخفي: قصير جداً"
    },
    "manuallyHidden": {
        "message": "مخفي يدوياً"
    },
    "invidiousPermissionRefresh": {
        "message": "قام المتصفح بإلغاء التصاريح المطلوبة للعمل على Invidious وغيرها من مواقع الطرف الثالث. الرجاء النقر على الزر أدناه لإعادة تنشيط هذا التصريح."
    },
    "acceptPermission": {
        "message": "قَبُول الإذن"
    },
    "permissionRequestSuccess": {
        "message": "نجح طلب الإذن!"
    },
    "permissionRequestFailed": {
        "message": "فشل طلب الإذن ، هل نقرت على رفض؟"
    },
    "adblockerIssueWhitelist": {
        "message": "إذا كنت غير قادر على حل هذا، عطل إعداد \"فرض قناة التحقق قبل التخطي\"، لأن SponsorBlock غير قادر على استرداد معلومات القناة لهذا المقطع"
    },
    "forceChannelCheck": {
        "message": "اجبار التحقق من القناة قبل التخطي"
    },
    "whatForceChannelCheck": {
        "message": "افتراضيا، سيتم تخطي الفقرات مباشرة حتى قبل التعرف على القناة. افتراضيا، قد يتم تخطي بعض الفقرات في بداية الفيديو على القنواة في اللائحة البيضاء. تفعيل هذا الخيار سيوقف ذلك لكن يجعل كل التخطيات لها تأخير طفيف حيث أن الحصول على معرف القناة قد يستغرق بعض الوقت. قد يكون هذا التأخير غير ملحوظ إذا كان لديك إنترنت سريع."
    },
    "downvoteDescription": {
        "message": "خاطئ/التوقيت غير صحيح"
    },
    "incorrectVote": {
        "message": "غير صحيح"
    },
    "harmfulVote": {
        "message": "ضار",
        "description": "Used for chapter segments when the text is harmful/offensive to remove it faster"
    },
    "incorrectCategory": {
        "message": "تغيير الفئة"
    },
    "nonMusicCategoryOnMusic": {
        "message": "هذا الفيديو مصنف كموسيقى. هل أنت متأكد من وجود رعاية؟ إن كانت هذه بالفعل \"فقرة غير موسيقية\"، قم بفتح خيارات الإضافة و فعّل هذه الفئة. ثم يمكنك تقديم هذه الفقرة كـ \"غير موسيقي\" بدلاً من رعاية. يرجى قراءة المبادئ التوجيهية إن كنت محتار."
    },
    "multipleSegments": {
        "message": "أجزاء متعددة"
    },
    "guidelines": {
        "message": "الإرشادات"
    },
    "readTheGuidelines": {
        "message": "اقرأ الإرشادات!!",
        "description": "Show the first time they submit or if they are \"high risk\""
    },
    "categoryUpdate1": {
        "message": "الفئات هنا!"
    },
    "categoryUpdate2": {
        "message": "افتح الخيارات لتخطي المقدمات و المؤخرات و ترويج المنتجات إلخ."
    },
    "help": {
        "message": "المساعدة"
    },
    "GotIt": {
        "message": "فهمت",
        "description": "Used as the button to dismiss a tooltip"
    },
    "hideForever": {
        "message": "إخفاء دائم"
    },
    "warningChatInfo": {
        "message": "لاحظنا أنك ترتكب بعض الأخطاء الشائعة. نحن نقدّر عملك حتى الآن، ولكننا نسعى جاهدين نحو الكمال، فحتى الأخطاء الصغيرة جدا مهمة :)"
    },
    "questionButton": {
        "message": "لدي سؤال"
    },
    "warningConfirmButton": {
        "message": "أنا أفهم السبب"
    },
    "Donate": {
        "message": "تبرع"
    },
    "considerDonating": {
        "message": "ساعد في تمويل التطوير"
    },
    "hideDonationLink": {
        "message": "إخفاء رابط التبرع"
    },
    "darkModeOptionsPage": {
        "message": "الوضع الداكن في صفحة الخيارات"
    },
    "helpPageThanksForInstalling": {
        "message": "شكرا على تثبيت SponsorBlock."
    },
    "helpPageReviewOptions": {
        "message": "يرجى مراجعة الخيارات أدناه"
    },
    "helpPageFeatureDisclaimer": {
        "message": "العديد من الميزات معطلة بشكل تلقائي. إذا كنت ترغب في تخطي المقدمة و الخاتمة و استخدام الدعوات و إلخ. يمكنك تمكين هذه الميزات بالأسفل. يمكنك أيضًا إخفاء و إظهار عناصر واجهة المستخدم."
    },
    "helpPageHowSkippingWorks": {
        "message": "كيف يعمل التخطي"
    },
    "helpPageHowSkippingWorks2": {
        "message": "كلما تتخطى فقرة، ستحصل على إشعار. إذا بدا التوقيت خاطئا بإمكانك التصويت سلبيا عبر ضغط زر التصويت السلبي! يمكنك أيضا التصويت في المنبثق."
    },
    "Submitting": {
        "message": "إرسال"
    },
    "Editing": {
        "message": "التعديل"
    },
    "helpPageTooSlow": {
        "message": "هذا بطيء جداً"
    },
    "helpPageCopyOfDatabase": {
        "message": "هل يمكنني الحصول على نسخة من قاعدة البيانات؟ ماذا يحدث إذا اختفيت؟"
    },
    "helpPageCopyOfDatabase1": {
        "message": "قاعدة البيانات عامة ومتاحة على"
    },
    "helpPageNews": {
        "message": "الأخبار وكيف تم صنعها"
    },
    "helpPageSourceCode": {
        "message": "أين يمكنني الحصول على شفرة المصدر؟"
    },
    "Credits": {
        "message": "المساهمون في العمل"
    },
    "LearnMore": {
        "message": "معرفة المزيد"
    },
    "FullDetails": {
        "message": "التفاصيل الكاملة"
    },
    "OpenCategoryWikiPage": {
        "message": "افتح صفحة ويكي هذه الفئة."
    },
    "CopyAndDownvote": {
        "message": "نسخ وتصويت معارض"
    },
    "ContinueVoting": {
        "message": "متابعة التصويت"
    },
    "downvote": {
        "message": "تصويت سلبي"
    },
    "upvote": {
        "message": "تصويت إيجابي"
    },
    "hideSegment": {
        "message": "إخفاء المقطع"
    },
    "playChapter": {
        "message": "شغل الفصل"
    },
    "SponsorTimeEditScrollNewFeature": {
        "message": "استخدم عجلة الماوس أثناء التمرير فوق مربع التعديل لضبط الوقت بسرعة. يمكن استخدام مجموعات مفتاح ctrl أو Shift لضبط التغييرات."
    },
    "dayAbbreviation": {
        "message": "ي",
        "description": "100d"
    },
    "hourAbbreviation": {
        "message": "س",
        "description": "100h"
    },
    "optionsTabBehavior": {
        "message": "سلوك",
        "description": "Appears in Options as a tab header for options related to categories and skipping behavior. To fit inside the button, it should not be longer than ~20-25 characters (depending on their width)."
    },
    "optionsTabInterface": {
        "message": "واجهه المستخدم",
        "description": "Appears in Options as a tab header for options related to GUI and sounds. To fit inside the button, it should not be longer than ~20-25 characters (depending on their width)."
    },
    "optionsTabKeyBinds": {
        "message": "اختصارات لوحة المفاتيح",
        "description": "Appears in Options as a tab header for keybinds. To fit inside the button, it should not be longer than ~20-25 characters (depending on their width)."
    },
    "optionsTabBackup": {
        "message": "النسخ الاحتياطي/الاستعادة",
        "description": "Appears in Options as a tab header for options related to saving/restoring your settings. To fit inside the button, it should not be longer than ~20-25 characters (depending on their width)."
    },
    "optionsTabAdvanced": {
        "message": "متنوع",
        "description": "Appears in Options as a tab header for advanced/niche options. To fit inside the button, it should not be longer than ~20-25 characters (depending on their width)."
    },
    "noticeVisibilityLabel": {
        "message": "مظهر إشعار التخطي",
        "description": "Option label"
    },
    "unbind": {
        "message": "إلغاء ربط",
        "description": "Unbind keyboard shortcut"
    },
    "notSet": {
        "message": "لم يتم التعيين"
    },
    "change": {
        "message": "تغيير"
    },
    "youtubeKeybindWarning": {
        "message": "هذا اختصار يوتيوب مدمج. هل أنت متأكد أنك تريد استخدامه؟"
    },
    "betaServerWarning": {
        "message": "الخادم التجريبي مفعّل!"
    },
    "openOptionsPage": {
        "message": "فتح صفحة الخيارات"
    },
    "resetToDefault": {
        "message": "إعادة تعيين الإعدادات الإفتراضية"
    },
    "confirmResetToDefault": {
        "message": "هل أنت متأكد من أنك تريد إعادة تعيين كافة الإعدادات إلى حالتها الافتراضية؟ لا يمكنك التراجع عن ذلك."
    },
    "exportSegments": {
        "message": "تصدير الفقرات"
    },
    "Import": {
        "message": "استورد",
        "description": "Button to initiate importing segments. Appears under the textbox where they paste in the data"
    },
    "hideUpsells": {
        "message": "إخفاء الخيارات غير المتاحة بدون دفع إضافي"
    },
    "hideNewFeatureUpdates": {
        "message": "إخفاء التنبيهات حول الميزات الجديدة"
    },
    "chooseACountry": {
        "message": "اختر البلد"
    },
    "noDiscount": {
        "message": "أنت لست مؤهلاً للحصول على خصم"
    },
    "discountLink": {
        "message": "رابط الخصم (انظر إلى السعر الوردي)"
    },
    "selectYourCountry": {
        "message": "اختر بلدك"
    },
    "patreonSignIn": {
        "message": "سجل مع بيتريون (Patreon)"
    },
    "unsubmittedSegmentCounts": {
        "message": "لديك حاليا {0} على {1}",
        "description": "Example: You currently have 12 unsubmitted segments on 5 videos"
    },
    "videosSingular": {
        "message": "مقطع",
        "description": "Example: You currently have 3 unsubmitted segments on 1 *video*"
    },
    "videosPlural": {
        "message": "مقاطع",
        "description": "Example: You currently have 12 unsubmitted segments on 5 *videos*"
    },
    "showUnsubmittedSegments": {
        "message": "أظهر الأجزاء",
        "description": "Show/hide button for the unsubmitted segments list"
    },
    "videoID": {
        "message": "معرف المقطع",
        "description": "Header of the unsubmitted segments list"
    },
    "actions": {
        "message": "قائمة الأوامر",
        "description": "Header of the unsubmitted segments list"
    },
    "exportSegmentsAsURL": {
        "message": "شارك كرابط"
    },
    "NoticeTimeAfterSkip": {
        "message": "{seconds} ثانية",
        "description": "This is used on the popup to show how much time left. It will look like \"5s\". The word {seconds} will be replaced, so keep it here. Translations should only change the \"s\""
    },
    "Start": {
        "message": "البداية"
    },
    "Middle": {
        "message": "الوسط"
    },
    "fetchTimeout": {
        "message": "انتهاء مهلة جلب البينات (مللي ثانية)"
    },
    "DeArrowPromotionMessage": {
        "message": "إيقاف طعم النقرة من خلال استبدال العناوين والصور المصغرة ببدائل أكثر دقة"
    },
    "DeArrowPromotionMessage2": {
        "message": "هل تعبت من طعم النقر؟ تفقد إضافتي الجديدة لتحسين العناوين والصور المصغرة"
    },
    "countReplacements": {
        "message": "قم بحساب تبديل العناوين و الصور المصغرة"
    },
    "YtNeuterMessage": {
        "message": "إضافة قائمة تصفية لمنع الاستطلاعات و المنتجات و العناصر الترويجية الأخرى باستخدام yt-neuter"
    },
    "requiresUblock": {
        "message": "يتطلب uBlock Origin"
    },
    "zoomToFillUnsupported": {
        "message": "SponsorBlock غير متوافق مع الإضافة \"Zoom to Fill\". هناك العديد من البدائل التي يمكنك استخدامها بدلاً من ذلك والتي ستعمل بشكل صحيح."
    },
    "freeTrialStarted": {
        "message": "بدأت النسخة التجربة المجانية الخاصة بك بنجاح. قم بزيارة اليوتيوب لتجربتها"
    },
    "freeTrialEnded": {
        "message": "انتهت النسخة التجريبية المجانية"
    },
    "freeTrialPrompt": {
        "message": "إذا كنت ترغب في التجربة لمدة ساعة، يمكنك بدء نسخة تجريبية مجانية بالزر أدناه."
    },
    "startFreeTrial": {
        "message": "ابدأ النسخة التجريبية المجانية"
    },
    "youCannotVoteDuringTrial": {
        "message": "لا يمكنك التصويت خلال النسخة التجريبية المجانية",
        "description": "Refers to voting for DeArrow titles and thumbnails"
    },
    "freeAccessRequested": {
        "message": "تم تسجيلك بنجاح للوصول المجاني. سيتم إعلامك عند منح الوصول المجاني."
    },
    "freeAccessComplete": {
        "message": "تهانينا! لديك الآن وصول مجاني إلى DeArrow"
    },
    "DeArrowNotActivated": {
        "message": "DeArrow غير مفعل"
    },
    "ActivateDeArrow": {
        "message": "تفعيل DeArrow"
    },
    "DeArrowIsActivated": {
        "message": "تم تفعيل DeArrow بنجاح"
    },
    "Close": {
        "message": "إغلاق"
    },
    "ViewLicenseKey": {
        "message": "اعرض مفتاح الرّخصة"
    },
    "SharingIsCaring": {
        "message": "المشاركة تعني الاهتمام"
    }
}